clustergnfwfit/__init__.py
clustergnfwfit/__main__.py
clustergnfwfit/beam_utils.py
clustergnfwfit/conversions.py
clustergnfwfit/demos.py
clustergnfwfit/di_utils.py
clustergnfwfit/eval_gnfw.py
clustergnfwfit/gnfw_fit_map.py
clustergnfwfit/mpfit.py
clustergnfwfit/mpfit_gNFW.py
clustergnfwfit/plot_utils.py
clustergnfwfit-0.0.6.dist-info/LICENSE
clustergnfwfit-0.0.6.dist-info/METADATA
clustergnfwfit-0.0.6.dist-info/WHEEL
clustergnfwfit-0.0.6.dist-info/top_level.txt
clustergnfwfit-0.0.6.dist-info/RECORD
