Metadata-Version: 2.1
Name: clustergnfwfit
Version: 0.0.6
Summary: Fits ACTPlank data to the gNFW model.
Author-email: Harry Lu <realharrylu@gmail.com>
Project-URL: Homepage, https://github.com/harrylu/clustergnfwfit_package
Project-URL: Bug Tracker, https://github.com/harrylu/clustergnfwfit_package/issues
Project-URL: ACTPlank Data, https://lambda.gsfc.nasa.gov/product/act/actpol_prod_table.html
Classifier: Programming Language :: Python :: 3
Classifier: License :: OSI Approved :: MIT License
Classifier: Operating System :: POSIX :: Linux
Classifier: Operating System :: MacOS
Classifier: Intended Audience :: Science/Research
Requires-Python: >=3.7
License-File: LICENSE
Requires-Dist: astropy (>=5.1)
Requires-Dist: matplotlib (>=3.5.3)
Requires-Dist: numpy (>=1.23.2)
Requires-Dist: pixell (>=0.16.0)
Requires-Dist: scipy (>=1.9.0)
